autobackgroundmodel/__init__.py
autobackgroundmodel/compress.py
autobackgroundmodel/count.py
autobackgroundmodel/fitbkg.py
autobackgroundmodel/fitbkgkde.py
autobackgroundmodel/plotcolors.py
bxa/__init__.py
bxa/sherpa/__init__.py
bxa/sherpa/cachedmodel.py
bxa/sherpa/galabs.py
bxa/sherpa/invgauss.py
bxa/sherpa/priors.py
bxa/sherpa/qq.py
bxa/sherpa/rebinnedmodel.py
bxa/sherpa/solver.py
bxa/sherpa/background/__init__.py
bxa/sherpa/background/chandra_1024.json
bxa/sherpa/background/erosita_1024.json
bxa/sherpa/background/fitters.py
bxa/sherpa/background/kde.py
bxa/sherpa/background/models.py
bxa/sherpa/background/nustar_4096.json
bxa/sherpa/background/pca.py
bxa/sherpa/background/suzaku_4096.json
bxa/sherpa/background/swift_xrt_1024.json
bxa/sherpa/background/xmm.py
bxa/sherpa/background/xmm_2400.json
bxa/sherpa/background/xmm_4096.json
bxa/sherpa/background/xmm_epn_1024.json
bxa/sherpa/background/xmm_epn_4096.json
bxa/sherpa/background/xrte_hexa_256.json
bxa/sherpa/background/xrte_hexb_256.json
bxa/sherpa/background/xrte_pca_128.json
bxa/xspec/__init__.py
bxa/xspec/gof.py
bxa/xspec/priors.py
bxa/xspec/qq.py
bxa/xspec/sinning.py
bxa/xspec/solver.py
bxa/xspec/workflow/plot_bxa.py
bxa/xspec/workflow/plot_xspec.py
bxa-5.1.1.data/scripts/addspec.py
bxa-5.1.1.data/scripts/bxa_fitbkg.py
bxa-5.1.1.data/scripts/bxa_fitbkgkde.py
bxa-5.1.1.data/scripts/fixkeywords.py
bxa-5.1.1.data/scripts/gal.py
bxa-5.1.1.dist-info/LICENSE
bxa-5.1.1.dist-info/METADATA
bxa-5.1.1.dist-info/WHEEL
bxa-5.1.1.dist-info/top_level.txt
bxa-5.1.1.dist-info/RECORD
