Metadata-Version: 2.2
Name: bxa
Version: 5.1.1
Summary: Bayesian X-ray spectral analysis
Home-page: https://github.com/JohannesBuchner/BXA/
Author: Johannes Buchner
Author-email: johannes.buchner.acad@gmx.com
License: GNU General Public License v3
Classifier: Development Status :: 5 - Production/Stable
Classifier: Intended Audience :: Science/Research
Classifier: Intended Audience :: Developers
Classifier: License :: OSI Approved :: GNU General Public License v3 (GPLv3)
Classifier: Natural Language :: English
Classifier: Programming Language :: Python :: 2
Classifier: Programming Language :: Python :: 2.7
Classifier: Programming Language :: Python :: 3
Classifier: Programming Language :: Python :: 3.5
Classifier: Programming Language :: Python :: 3.6
Classifier: Programming Language :: Python :: 3.7
License-File: LICENSE
Requires-Dist: ultranest
Requires-Dist: numpy
Requires-Dist: tqdm
Requires-Dist: corner
Requires-Dist: h5py
Requires-Dist: matplotlib
Requires-Dist: astropy
Requires-Dist: natsort
Requires-Dist: joblib
Dynamic: author
Dynamic: author-email
Dynamic: classifier
Dynamic: description
Dynamic: home-page
Dynamic: license
Dynamic: requires-dist
Dynamic: summary
